{"data":{"allMarkdownRemark":{"totalCount":5,"edges":[{"node":{"id":"57b59a6b-5f78-5a9d-875a-f016313f7e65","frontmatter":{"title":"Service design alpha","location":"Department for Education","type":"Contract"},"fields":{"slug":"/works/dfe-nrs-alpha/"},"excerpt":""}},{"node":{"id":"9901cca0-c431-5b8a-87d2-5cb0b1b242bc","frontmatter":{"title":"User research discovery","location":"Department for Education","type":"Contract"},"fields":{"slug":"/works/dfe-parents-disco/"},"excerpt":""}},{"node":{"id":"bf862393-2af4-5457-8ebe-31f1dd8dd885","frontmatter":{"title":"Service design alpha","location":"Department for Education","type":"Contract"},"fields":{"slug":"/works/dfe-single-place-alpha/"},"excerpt":""}},{"node":{"id":"fb83094e-0169-5163-84b9-0aebf2441568","frontmatter":{"title":"","location":null,"type":"Project"},"fields":{"slug":"/works/whitechapel/"},"excerpt":""}},{"node":{"id":"ae150b60-f5b7-51f5-ae77-efc712fab339","frontmatter":{"title":"","location":null,"type":"Role"},"fields":{"slug":"/works/decoded/"},"excerpt":""}}]}},"pageContext":{"isCreatedByStatefulCreatePages":true}}